AUTHORS
LICENSE
MANIFEST.in
README.md
setup.py
django_imagefit.egg-info/PKG-INFO
django_imagefit.egg-info/SOURCES.txt
django_imagefit.egg-info/dependency_links.txt
django_imagefit.egg-info/not-zip-safe
django_imagefit.egg-info/requires.txt
django_imagefit.egg-info/top_level.txt
imagefit/__init__.py
imagefit/conf.py
imagefit/models.py
imagefit/urls.py
imagefit/views.py
imagefit/templatetags/__init__.py
imagefit/templatetags/imagefit.py