Metadata-Version: 2.1
Name: django-imagefit
Version: 0.8.0
Summary: Render an optimized version of your original image on display. Ability to resize and crop.
Home-page: http://github.com/vinyll/django-imagefit
Author: Vincent Agnano
Author-email: vinyll@protonmail.com
License: BSD
Classifier: Environment :: Web Environment
Classifier: Intended Audience :: Developers
Classifier: License :: OSI Approved :: BSD License
Classifier: Operating System :: OS Independent
Classifier: Programming Language :: Python
Classifier: Programming Language :: Python :: 2.6
Classifier: Programming Language :: Python :: 3.3
Classifier: Topic :: Utilities
License-File: LICENSE
License-File: AUTHORS
